elem_hasplib/__init__.py
elem_hasplib/elem_hasplib_cli.py
elem_hasplib/hasp_mgr
elem_hasplib/aksusbd/EMSUrl.properties
elem_hasplib/aksusbd/dinst
elem_hasplib/aksusbd/dunst
elem_hasplib/aksusbd/haspvlib_32042.so
elem_hasplib/aksusbd/haspvlib_x86_64_32042.so
elem_hasplib/aksusbd/bin/aksusbd
elem_hasplib/aksusbd/bin/aksusbd.rc
elem_hasplib/aksusbd/bin/aksusbd.service
elem_hasplib/aksusbd/bin/aksusbd_x86_64
elem_hasplib/aksusbd/bin/aksusbd_x86_64.service
elem_hasplib/aksusbd/bin/de.18.0.alp
elem_hasplib/aksusbd/bin/es.18.0.alp
elem_hasplib/aksusbd/bin/fr.18.0.alp
elem_hasplib/aksusbd/bin/hasp.rules
elem_hasplib/aksusbd/bin/hasp_arm.rules
elem_hasplib/aksusbd/bin/hasp_x86_64.rules
elem_hasplib/aksusbd/bin/hasplmd
elem_hasplib/aksusbd/bin/hasplmd.service
elem_hasplib/aksusbd/bin/hasplmd_arm64
elem_hasplib/aksusbd/bin/hasplmd_arm64.service
elem_hasplib/aksusbd/bin/hasplmd_armhf
elem_hasplib/aksusbd/bin/hasplmd_armhf.service
elem_hasplib/aksusbd/bin/hasplmd_x86_64
elem_hasplib/aksusbd/bin/hasplmd_x86_64.service
elem_hasplib/aksusbd/bin/install_v2c
elem_hasplib/aksusbd/bin/install_v2c_arm64
elem_hasplib/aksusbd/bin/install_v2c_armhf
elem_hasplib/aksusbd/bin/install_v2c_x86_64
elem_hasplib/aksusbd/bin/it.18.0.alp
elem_hasplib/aksusbd/bin/ja.18.0.alp
elem_hasplib/aksusbd/bin/ru.18.0.alp
elem_hasplib/aksusbd/bin/zh-CN.18.0.alp
elem_hasplib/aksusbd/pkg/aksusbd-8.43-1.aarch64.rpm
elem_hasplib/aksusbd/pkg/aksusbd-8.43-1.armv7hl.rpm
elem_hasplib/aksusbd/pkg/aksusbd-8.43-1.i386.rpm
elem_hasplib/aksusbd/pkg/aksusbd-8.43-1.x86_64.rpm
elem_hasplib/aksusbd/pkg/aksusbd_8.43-1_amd64.deb
elem_hasplib/aksusbd/pkg/aksusbd_8.43-1_arm64.deb
elem_hasplib/aksusbd/pkg/aksusbd_8.43-1_armhf.deb
elem_hasplib/aksusbd/pkg/aksusbd_8.43-1_i386.deb
elem_hasplib/config/cpu.json
elem_hasplib/config/gpu.json
elem_hasplib/config/hasplm.ini
elem_hasplib-1.0.0.dist-info/METADATA
elem_hasplib-1.0.0.dist-info/WHEEL
elem_hasplib-1.0.0.dist-info/entry_points.txt
elem_hasplib-1.0.0.dist-info/top_level.txt
elem_hasplib-1.0.0.dist-info/RECORD
