Metadata-Version: 2.1
Name: elem-hasplib
Version: 1.0.0
Summary: bisheng-rt-enterprice authorize module
Home-page: https://github.com/dataelement/bisheng
Author: DataElem
Author-email: contact@dataelem.com
License: Apache 2.0
Classifier: Programming Language :: Python :: 3
Classifier: Programming Language :: Python :: 3.6
Classifier: Programming Language :: Python :: 3.7
Classifier: Programming Language :: Python :: 3.8
Classifier: Programming Language :: Python :: 3.9
Classifier: License :: OSI Approved :: Apache Software License
Classifier: Operating System :: OS Independent
Requires-Python: >=3.6
